{"data":{"experiences":{"edges":[{"node":{"id":"37ebe940-d500-5faf-aa0c-52a0f661301b","title":"Ediket","title_detail":"React・GraphQL・Relay","category":"work","desc":"주로 ediket.com 프론트엔드 개발을 하였으며 GraphQL 서버, 관리자 사이트, Android Hybrid PWA앱도 개발 하였습니다.","location":"Seoul","startedAt":"2014.12","url":"https://ediket.com/","pinned":true}},{"node":{"id":"9a00ffec-a3ce-5d7c-8e54-ae7969ac986a","title":"SVWebGL at nVidia with Mr.Doob","title_detail":null,"category":"meetup","desc":"WebGL Developers Meetup","location":"San Francisco, CA","startedAt":"2016.09","url":"https://www.meetup.com/WebGL-Developers-Meetup/events/234336450/","pinned":true}},{"node":{"id":"7d6dab9b-c1f6-5626-9480-bf16d1ea2e08","title":"블랙라벨 데이팅","title_detail":"React Native・Typescript・Apollo","category":"work","desc":"블랙라벨 데이팅 iOS/Android 앱 개발하였습니다.","location":"Seoul","startedAt":"2019.02","url":"https://play.google.com/store/apps/details?id=com.blackLabel.blackLabelApp","pinned":true}},{"node":{"id":"83c83008-21a9-5053-aa27-0e7d8b70787b","title":"Apitii","title_detail":"next.js・Prisma・Apollo","category":"hobby","desc":"취미로 만들고 있는 레시피 공유 사이트 입니다.","location":"Seoul","startedAt":"2018.11","url":"https://apitii.com/","pinned":true}}]}}}